cbi_webengines/__init__.py
cbi_webengines/interfaces/__init__.py
cbi_webengines/interfaces/application.py
cbi_webengines/interfaces/data_request.py
cbi_webengines/interfaces/data_response.py
cbi_webengines/interfaces/engine_repository.py
cbi_webengines/interfaces/errors.py
cbi_webengines/interfaces/handler.py
cbi_webengines/interfaces/header.py
cbi_webengines/interfaces/router.py
cbi_webengines/interfaces/middleware/__init__.py
cbi_webengines/interfaces/middleware/middleware.py
cbi_webengines/interfaces/servers/__init__.py
cbi_webengines/interfaces/servers/server.py
cbi_webengines/interfaces/servers/uvicorn_server.py
cbi_webengines/interfaces/settings/__init__.py
cbi_webengines/interfaces/settings/base_engine_app_settings.py
cbi_webengines/interfaces/settings/cors_settings.py
cbi_webengines/interfaces/settings/web_settings.py
cbi_webengines/repositories/__init__.py
cbi_webengines/repositories/application_repository.py
cbi_webengines/repositories/engines/__init__.py
cbi_webengines/repositories/engines/fastapi_engine_repository.py
tests/__init__.py
tests/conftest.py
tests/fixtures/__init__.py
tests/fixtures/fastapi_apps.py
tests/fixtures/servers.py
tests/test_interfaces/__init__.py
tests/test_interfaces/test_servers/__init__.py
tests/test_interfaces/test_servers/test_base_server.py
tests/test_interfaces/test_servers/test_uvicorn_server.py
tests/test_repositories/__init__.py
tests/test_repositories/test_application_repository/__init__.py
tests/test_repositories/test_application_repository/test_fastapi_app.py
cbi_webengines-1.1.1.dist-info/LICENSE
cbi_webengines-1.1.1.dist-info/METADATA
cbi_webengines-1.1.1.dist-info/WHEEL
cbi_webengines-1.1.1.dist-info/top_level.txt
cbi_webengines-1.1.1.dist-info/zip-safe
cbi_webengines-1.1.1.dist-info/RECORD
